{
  "plugins": {
    "blink-nerdfont.nvim": {
      "rev": "e5034457a0a3f3444c0a48af8f5d7db0ad02a204",
      "src": "https://github.com/MahanRahmati/blink-nerdfont.nvim"
    },
    "blink.cmp": {
      "rev": "4b18c32adef2898f95cdef6192cbd5796c1a332d",
      "src": "https://github.com/saghen/blink.cmp"
    },
    "bullets.vim": {
      "rev": "89294b8930e660936374fb763ac48a1ac51dd29c",
      "src": "https://github.com/bullets-vim/bullets.vim"
    },
    "conform.nvim": {
      "rev": "c2526f1cde528a66e086ab1668e996d162c75f4f",
      "src": "https://github.com/stevearc/conform.nvim"
    },
    "desert-witch.nvim": {
      "rev": "88810d0263482efdc69a1f6c5e5fe9f6f0a2e495",
      "src": "https://codeberg.org/trickyni/desert-witch.nvim"
    },
    "gitsigns.nvim": {
      "rev": "31217271a7314c343606acb4072a94a039a19fb5",
      "src": "https://github.com/lewis6991/gitsigns.nvim"
    },
    "guttermarks.nvim": {
      "rev": "b57e6dd1f29b378d2dc8ae5097a7710c3ef328be",
      "src": "https://github.com/dimtion/guttermarks.nvim"
    },
    "live-command.nvim": {
      "rev": "fc8c36d7e5b96945fbc52af7029facc317a47377",
      "src": "https://github.com/smjonas/live-command.nvim"
    },
    "lualine.nvim": {
      "rev": "47f91c416daef12db467145e16bed5bbfe00add8",
      "src": "https://github.com/nvim-lualine/lualine.nvim"
    },
    "lz.n": {
      "rev": "5825c810ac97e141fb8869e3dabef06653ac6ecd",
      "src": "https://github.com/lumen-oss/lz.n"
    },
    "markdown-preview.nvim": {
      "rev": "a923f5fc5ba36a3b17e289dc35dc17f66d0548ee",
      "src": "https://github.com/iamcco/markdown-preview.nvim"
    },
    "mini.align": {
      "rev": "6d8a6ca3a0fd313938374abccb50cad026229db3",
      "src": "https://github.com/nvim-mini/mini.align"
    },
    "mini.comment": {
      "rev": "a0c721115faff8d05505c0a12dab410084d9e536",
      "src": "https://github.com/nvim-mini/mini.comment"
    },
    "mini.move": {
      "rev": "4d214202d71e0a4066b6288176bbe88f268f9777",
      "src": "https://github.com/nvim-mini/mini.move"
    },
    "mini.pairs": {
      "rev": "4089aa6ea6423e02e1a8326a7a7a00159f6f5e04",
      "src": "https://github.com/nvim-mini/mini.pairs"
    },
    "mini.splitjoin": {
      "rev": "9fcd8856efb95a505090c3225726466494076127",
      "src": "https://github.com/nvim-mini/mini.splitjoin"
    },
    "mini.surround": {
      "rev": "d648a5601e1c48f175b07d10eba141da338a0a2a",
      "src": "https://github.com/nvim-mini/mini.surround"
    },
    "mini.tabline": {
      "rev": "caf23615b9b99bacc79ecd60f61c4e6a8ec18c84",
      "src": "https://github.com/nvim-mini/mini.tabline"
    },
    "neoscroll.nvim": {
      "rev": "c8d29979cb0cb3a2437a8e0ae683fd82f340d3b8",
      "src": "https://github.com/karb94/neoscroll.nvim"
    },
    "nvim-colorizer.lua": {
      "rev": "338409dd8a6ed74767bad3eb5269f1b903ffb3cf",
      "src": "https://github.com/catgoose/nvim-colorizer.lua"
    },
    "nvim-rip-substitute": {
      "rev": "1fae57ead7e1f3221286beced9e32fdd661e453b",
      "src": "https://github.com/chrisgrieser/nvim-rip-substitute"
    },
    "nvim-treesitter": {
      "rev": "9f2dad22ef8bb14fd1e0a3aa8859cdc88170668b",
      "src": "https://github.com/nvim-treesitter/nvim-treesitter"
    },
    "nvim-web-devicons": {
      "rev": "746ffbb17975ebd6c40142362eee1b0249969c5c",
      "src": "https://github.com/nvim-tree/nvim-web-devicons"
    },
    "plenary.nvim": {
      "rev": "b9fd5226c2f76c951fc8ed5923d85e4de065e509",
      "src": "https://github.com/nvim-lua/plenary.nvim"
    },
    "rainbow-delimiters.nvim": {
      "rev": "d6b802552cbe7d643a3b6b31f419c248d1f1e220",
      "src": "https://gitlab.com/HiPhish/rainbow-delimiters.nvim"
    },
    "render-markdown.nvim": {
      "rev": "48b4175dbca8439d30c1f52231cbe5a712c8f9d9",
      "src": "https://github.com/MeanderingProgrammer/render-markdown.nvim"
    },
    "snacks.nvim": {
      "rev": "fe7cfe9800a182274d0f868a74b7263b8c0c020b",
      "src": "https://github.com/folke/snacks.nvim"
    },
    "tabout.nvim": {
      "rev": "9a3499480a8e53dcaa665e2836f287e3b7764009",
      "src": "https://github.com/abecodes/tabout.nvim"
    },
    "todo-comments.nvim": {
      "rev": "31e3c38ce9b29781e4422fc0322eb0a21f4e8668",
      "src": "https://github.com/folke/todo-comments.nvim"
    },
    "trouble.nvim": {
      "rev": "bd67efe408d4816e25e8491cc5ad4088e708a69a",
      "src": "https://github.com/folke/trouble.nvim"
    },
    "which-key.nvim": {
      "rev": "3aab2147e74890957785941f0c1ad87d0a44c15a",
      "src": "https://github.com/folke/which-key.nvim"
    },
    "yazi.nvim": {
      "rev": "3d8e2e23bef09b41f405f11e0147a9d0793d2ef8",
      "src": "https://github.com/mikavilpas/yazi.nvim"
    },
    "zen-mode.nvim": {
      "rev": "8564ce6d29ec7554eb9df578efa882d33b3c23a7",
      "src": "https://github.com/folke/zen-mode.nvim"
    }
  }
}